Metadata-Version: 2.1
Name: django-spread
Version: 1.0.1
Summary: Django Spread Integration
Home-page: https://gitlab.com/linets/ecommerce/oms/integrations/django-spread/
Author: Linets Development Team
Author-email: dteam@linets.cl
License: MIT
Platform: UNKNOWN
Requires-Python: >=3.7
License-File: LICENSE
